ose_plugin_addicto/AddictOVocabClient.py
ose_plugin_addicto/AddictOVocabReleaseStep.py
ose_plugin_addicto/AddictOVocabService.py
ose_plugin_addicto/__init__.py
ose_plugin_addicto/main.py
ose_plugin_addicto/static/ose-plugin-addicto.js
ose_plugin_addicto/static/ose-plugin-addicto.umd.cjs
ose_plugin_addicto-0.2.5.dist-info/METADATA
ose_plugin_addicto-0.2.5.dist-info/WHEEL
ose_plugin_addicto-0.2.5.dist-info/entry_points.txt
ose_plugin_addicto-0.2.5.dist-info/top_level.txt
ose_plugin_addicto-0.2.5.dist-info/RECORD
