Metadata-Version: 2.4
Name: ose-plugin-addicto
Version: 0.2.5
Summary: OntoSpreadEd plugin for AddictO services and workflows
Requires-Python: >=3.12
Requires-Dist: ose-core==0.2.5
Requires-Dist: ose-plugin-hbcp==0.2.5
